biosynth/BioSynth.py
biosynth/__init__.py
biosynth/__main__.py
biosynth/algorithm/__init__.py
biosynth/algorithm/eliminate_sequence.py
biosynth/algorithm/fsm.py
biosynth/app-debug.py
biosynth/data/__init__.py
biosynth/data/app_data.py
biosynth/executions/__init__.py
biosynth/executions/controllers/__init__.py
biosynth/executions/controllers/cli_controller.py
biosynth/executions/controllers/command_controller.py
biosynth/executions/controllers/debug_controller.py
biosynth/executions/controllers/gui_controller.py
biosynth/executions/controllers/ui/base_window.py
biosynth/executions/controllers/ui/elimination_window.py
biosynth/executions/controllers/ui/results_window.py
biosynth/executions/controllers/ui/settings_window.py
biosynth/executions/controllers/ui/upload_window.py
biosynth/executions/controllers/ui/window_utils.py
biosynth/executions/execution_utils.py
biosynth/executions/ui/__init__.py
biosynth/images/BioSynth-Transparent.png
biosynth/images/BioSynth.png
biosynth/report/__init__.py
biosynth/report/html_report_utils.py
biosynth/report/report.html
biosynth/settings/__init__.py
biosynth/settings/codon_usage_settings.py
biosynth/settings/pattern_settings.py
biosynth/settings/sequence_settings.py
biosynth/test/__init__.py
biosynth/test/test_app_data.py
biosynth/test/test_cost_utils.py
biosynth/test/test_dna_utils.py
biosynth/test/test_elimination_utils.py
biosynth/test/test_file_utils.py
biosynth/test/test_fsm.py
biosynth/test/test_info_utils.py
biosynth/test/test_input_utils.py
biosynth/test/test_output_utils.py
biosynth/test/test_text_utils.py
biosynth/utils/__init__.py
biosynth/utils/amino_acid_utils.py
biosynth/utils/cost_utils.py
biosynth/utils/date_utils.py
biosynth/utils/display_utils.py
biosynth/utils/dna_utils.py
biosynth/utils/file_utils.py
biosynth/utils/info_utils.py
biosynth/utils/input_utils.py
biosynth/utils/output_utils.py
biosynth/utils/text_utils.py
biosynth_tool-1.1.0.dist-info/LICENSE
biosynth_tool-1.1.0.dist-info/METADATA
biosynth_tool-1.1.0.dist-info/WHEEL
biosynth_tool-1.1.0.dist-info/entry_points.txt
biosynth_tool-1.1.0.dist-info/RECORD
