Metadata-Version: 2.3
Name: biosynth-tool
Version: 1.1.0
Summary: BioSynth is a synthetic DNA design tool that eliminates unwanted patterns from sequences using a biologically informed cost model and optimized algorithms. It leverages a finite state machine with two-base memory and dynamic programming to generate minimum-cost sequences that preserve protein function, respect codon usage bias, and avoid unwanted patterns. The tool provides both GUI and CLI interfaces for flexible and efficient DNA design workflows.
License: Apache-2.0
Author: Hadar Pur
Author-email: hadarpur13@gmail.com
Requires-Python: >=3.9,<4.0
Classifier: License :: OSI Approved :: Apache Software License
Classifier: Programming Language :: Python :: 3
Classifier: Programming Language :: Python :: 3.9
Classifier: Programming Language :: Python :: 3.10
Classifier: Programming Language :: Python :: 3.11
Classifier: Programming Language :: Python :: 3.12
Classifier: Programming Language :: Python :: 3.13
Requires-Dist: Jinja2 (>=3.1.6,<4.0.0)
Requires-Dist: PyQt5 (>=5.15.9,<6.0.0)
Requires-Dist: bio (>=1.6.2,<2.0.0)
Requires-Dist: biopython (>=1.85,<2.0)
Requires-Dist: numpy (>=1.26.4,<2.0.0)
Requires-Dist: pywebview (>=5.4,<6.0)
